pydantic_shodan/__init__.py
pydantic_shodan/models.py
pydantic_shodan-1.1.0.dist-info/METADATA
pydantic_shodan-1.1.0.dist-info/WHEEL
pydantic_shodan-1.1.0.dist-info/top_level.txt
pydantic_shodan-1.1.0.dist-info/RECORD
