Metadata-Version: 2.1
Name: pydantic-shodan
Version: 1.1.0
Summary: Pydantic model for Shodan banner
Home-page: https://github.com/gethvi/pydantic-shodan
Author: Gethvi
License: Apache-2.0
Platform: UNKNOWN
Requires-Dist: pydantic (>=1.8.2)
